openadapt_viewer/__init__.py
openadapt_viewer/catalog.py
openadapt_viewer/catalog_api.py
openadapt_viewer/cli.py
openadapt_viewer/scanner.py
openadapt_viewer/search.js
openadapt_viewer/segmentation_catalog.py
openadapt_viewer/builders/__init__.py
openadapt_viewer/builders/page_builder.py
openadapt_viewer/components/__init__.py
openadapt_viewer/components/action_display.py
openadapt_viewer/components/action_filter.py
openadapt_viewer/components/action_timeline.py
openadapt_viewer/components/badge.py
openadapt_viewer/components/comparison.py
openadapt_viewer/components/episode_timeline.js
openadapt_viewer/components/failure_analysis.py
openadapt_viewer/components/filters.py
openadapt_viewer/components/list_view.py
openadapt_viewer/components/metrics.py
openadapt_viewer/components/playback.py
openadapt_viewer/components/screenshot.py
openadapt_viewer/components/timeline.py
openadapt_viewer/components/video_playback.py
openadapt_viewer/core/__init__.py
openadapt_viewer/core/data_loader.py
openadapt_viewer/core/html_builder.py
openadapt_viewer/core/types.py
openadapt_viewer/examples/__init__.py
openadapt_viewer/examples/benchmark_example.py
openadapt_viewer/examples/capture_example.py
openadapt_viewer/examples/enhanced_capture_example.py
openadapt_viewer/examples/retrieval_example.py
openadapt_viewer/examples/training_example.py
openadapt_viewer/js/README.md
openadapt_viewer/js/filters.js
openadapt_viewer/js/search.js
openadapt_viewer/js/utils.js
openadapt_viewer/styles/core.css
openadapt_viewer/styles/episode_timeline.css
openadapt_viewer/templates/base.html
openadapt_viewer/templates/components/header.html
openadapt_viewer/templates/components/navigation.html
openadapt_viewer/viewers/__init__.py
openadapt_viewer/viewers/segmentation_generator.py
openadapt_viewer/viewers/benchmark/__init__.py
openadapt_viewer/viewers/benchmark/data.py
openadapt_viewer/viewers/benchmark/generator.py
openadapt_viewer/viewers/benchmark/real_data_loader.py
openadapt_viewer-0.2.0.dist-info/METADATA
openadapt_viewer-0.2.0.dist-info/WHEEL
openadapt_viewer-0.2.0.dist-info/entry_points.txt
openadapt_viewer-0.2.0.dist-info/licenses/LICENSE
openadapt_viewer-0.2.0.dist-info/RECORD
