Metadata-Version: 2.4
Name: openadapt-viewer
Version: 0.2.0
Summary: Standalone HTML viewer generation for OpenAdapt ML dashboards and benchmarks
Project-URL: Homepage, https://github.com/OpenAdaptAI/openadapt-viewer
Project-URL: Repository, https://github.com/OpenAdaptAI/openadapt-viewer
Project-URL: Documentation, https://github.com/OpenAdaptAI/openadapt-viewer#readme
Project-URL: Issues, https://github.com/OpenAdaptAI/openadapt-viewer/issues
Project-URL: Changelog, https://github.com/OpenAdaptAI/openadapt-viewer/releases
Author-email: Richard Abrich <richard@openadapt.ai>
Maintainer: OpenAdaptAI
License-Expression: MIT
License-File: LICENSE
Keywords: benchmarks,dashboard,html,ml,viewer,visualization
Classifier: Development Status :: 3 - Alpha
Classifier: Intended Audience :: Developers
Classifier: License :: OSI Approved :: MIT License
Classifier: Programming Language :: Python :: 3
Classifier: Programming Language :: Python :: 3.10
Classifier: Programming Language :: Python :: 3.11
Classifier: Programming Language :: Python :: 3.12
Classifier: Topic :: Scientific/Engineering :: Visualization
Classifier: Topic :: Software Development :: Libraries :: Python Modules
Requires-Python: >=3.10
Requires-Dist: imageio>=2.37.2
Requires-Dist: jinja2>=3.1.0
Requires-Dist: pillow>=10.0.0
Requires-Dist: playwright>=1.57.0
Requires-Dist: plotly>=5.18.0
Requires-Dist: pydantic>=2.0.0
Provides-Extra: all
Requires-Dist: playwright>=1.40.0; extra == 'all'
Requires-Dist: pytest>=8.0.0; extra == 'all'
Requires-Dist: ruff>=0.1.0; extra == 'all'
Provides-Extra: dev
Requires-Dist: pytest>=8.0.0; extra == 'dev'
Requires-Dist: ruff>=0.1.0; extra == 'dev'
Provides-Extra: screenshots
Requires-Dist: playwright>=1.40.0; extra == 'screenshots'
